[
	{
		"id": "accordions",
		"icon": "fa-list",
		"x": 770,
		"y": 350,
		"type": "plugin"
	},
	{
		"id": "icons",
		"icon": "fa-star",
		"x": 770,
		"y": 500,
		"type": "plugin"
	},
	{
		"id": "images",
		"icon": "fa-camera",
		"x": 770,
		"y": 600,
		"type": "plugin"
	},
	{
		"id": "media",
		"icon": "fa-play",
		"x": 770,
		"y": 420,
		"type": "plugin"
	},
	{
		"id": "notifications",
		"icon": "fa-bullhorn",
		"x": 770,
		"y": 630,
		"type": "plugin"
	},
	{
		"id": "tabs",
		"icon": "fa-folder-o",
		"x": 770,
		"y": 420,
		"type": "plugin"
	}
]